dsw/tdk/__init__.py
dsw/tdk/__main__.py
dsw/tdk/api_client.py
dsw/tdk/build_info.py
dsw/tdk/cli.py
dsw/tdk/config.py
dsw/tdk/consts.py
dsw/tdk/core.py
dsw/tdk/model.py
dsw/tdk/utils.py
dsw/tdk/validation.py
dsw/tdk/templates/LICENSE.j2
dsw/tdk/templates/README.md.j2
dsw/tdk/templates/env.j2
dsw/tdk/templates/starter.j2
dsw_tdk-4.26.1.dist-info/licenses/LICENSE
dsw_tdk-4.26.1.dist-info/METADATA
dsw_tdk-4.26.1.dist-info/WHEEL
dsw_tdk-4.26.1.dist-info/entry_points.txt
dsw_tdk-4.26.1.dist-info/top_level.txt
dsw_tdk-4.26.1.dist-info/RECORD
