Metadata-Version: 2.4
Name: dsw-tdk
Version: 4.26.1
Summary: Data Stewardship Wizard Template Development Toolkit
Author-email: Marek Suchánek <marek.suchanek@ds-wizard.org>
License: Apache License 2.0
Project-URL: Homepage, https://ds-wizard.org
Project-URL: Repository, https://github.com/ds-wizard/engine-tools
Project-URL: Documentation, https://guide.ds-wizard.org
Keywords: documents,dsw,jinja2,template,toolkit
Classifier: Framework :: AsyncIO
Classifier: Development Status :: 5 - Production/Stable
Classifier: License :: OSI Approved :: Apache Software License
Classifier: Programming Language :: Python
Classifier: Programming Language :: Python :: 3.10
Classifier: Programming Language :: Python :: 3.11
Classifier: Programming Language :: Python :: 3.12
Classifier: Programming Language :: Python :: 3.13
Classifier: Topic :: Internet :: WWW/HTTP
Classifier: Topic :: Utilities
Requires-Python: <4,>=3.10
License-File: LICENSE
Requires-Dist: aiohttp
Requires-Dist: click
Requires-Dist: colorama
Requires-Dist: humanize
Requires-Dist: Jinja2
Requires-Dist: multidict
Requires-Dist: pathspec
Requires-Dist: python-dotenv
Requires-Dist: python-slugify
Requires-Dist: watchfiles
Provides-Extra: test
Requires-Dist: pytest; extra == "test"
Dynamic: license-file
